<?xml version="1.0" encoding="UTF-8"?>
<mule xmlns="http://www.mulesoft.org/schema/mule/core" xmlns:apikit="http://www.mulesoft.org/schema/mule/mule-apikit" xmlns:doc="http://www.mulesoft.org/schema/mule/documentation" xmlns:ee="http://www.mulesoft.org/schema/mule/ee/core" xmlns:http="http://www.mulesoft.org/schema/mule/http" xmlns:validation="http://www.mulesoft.org/schema/mule/validation" xmlns:xsi="http://www.w3.org/2001/XMLSchema-instance" xsi:schemaLocation="http://www.mulesoft.org/schema/mule/core http://www.mulesoft.org/schema/mule/core/current/mule.xsd http://www.mulesoft.org/schema/mule/http http://www.mulesoft.org/schema/mule/http/current/mule-http.xsd http://www.mulesoft.org/schema/mule/mule-apikit http://www.mulesoft.org/schema/mule/mule-apikit/current/mule-apikit.xsd  http://www.mulesoft.org/schema/mule/ee/core http://www.mulesoft.org/schema/mule/ee/core/current/mule-ee.xsd http://www.mulesoft.org/schema/mule/validation http://www.mulesoft.org/schema/mule/validation/current/mule-validation.xsd">
    <http:listener-config name="exampleprep-httpListenerConfig1">
        <http:listener-connection host="0.0.0.0" port="8081" />
    </http:listener-config>
    <apikit:config name="exampleprep-config2" raml="exampleprep.raml" outboundHeadersMapName="outboundHeaders" httpStatusVarName="httpStatus" />
    <validation:config name="Validation_Config" doc:name="Validation Config" doc:id="54281e6e-71f8-4d9a-9aef-4bfa002303ce" />
    <flow name="exampleprep-main">
        <http:listener config-ref="exampleprep-httpListenerConfig1" path="/api/*">
            <http:response statusCode="#[vars.httpStatus default 200]">
                <http:headers><![CDATA[#[vars.outboundHeaders default {}]]]></http:headers>
            </http:response>
            <http:error-response statusCode="#[vars.httpStatus default 500]">
                <http:body><![CDATA[#[payload]]]></http:body>
                <http:headers><![CDATA[#[vars.outboundHeaders default {}]]]></http:headers>
            </http:error-response>
        </http:listener>
        <apikit:router config-ref="exampleprep-config2" />
        <error-handler>
            <on-error-propagate type="APIKIT:BAD_REQUEST" enableNotifications="true" logException="true">
                <ee:transform xsi:schemaLocation="http://www.mulesoft.org/schema/mule/ee/core http://www.mulesoft.org/schema/mule/ee/core/current/mule-ee.xsd">
                    <ee:message>
                        <ee:set-payload><![CDATA[%dw 2.0
output application/json
---
{message: "Bad request"}]]></ee:set-payload>
                    </ee:message>
                    <ee:variables>
                        <ee:set-variable variableName="httpStatus">400</ee:set-variable>
                    </ee:variables>
                </ee:transform>
            </on-error-propagate>
            <on-error-propagate type="APIKIT:NOT_FOUND" enableNotifications="true" logException="true">
                <ee:transform xsi:schemaLocation="http://www.mulesoft.org/schema/mule/ee/core http://www.mulesoft.org/schema/mule/ee/core/current/mule-ee.xsd">
                    <ee:message>
                        <ee:set-payload><![CDATA[%dw 2.0
output application/json
---
{message: "Resource not found"}]]></ee:set-payload>
                    </ee:message>
                    <ee:variables>
                        <ee:set-variable variableName="httpStatus">404</ee:set-variable>
                    </ee:variables>
                </ee:transform>
            </on-error-propagate>
            <on-error-propagate type="APIKIT:METHOD_NOT_ALLOWED" enableNotifications="true" logException="true">
                <ee:transform xsi:schemaLocation="http://www.mulesoft.org/schema/mule/ee/core http://www.mulesoft.org/schema/mule/ee/core/current/mule-ee.xsd">
                    <ee:message>
                        <ee:set-payload><![CDATA[%dw 2.0
output application/json
---
{message: "Method not allowed"}]]></ee:set-payload>
                    </ee:message>
                    <ee:variables>
                        <ee:set-variable variableName="httpStatus">405</ee:set-variable>
                    </ee:variables>
                </ee:transform>
            </on-error-propagate>
            <on-error-propagate type="APIKIT:NOT_ACCEPTABLE" enableNotifications="true" logException="true">
                <ee:transform xsi:schemaLocation="http://www.mulesoft.org/schema/mule/ee/core http://www.mulesoft.org/schema/mule/ee/core/current/mule-ee.xsd">
                    <ee:message>
                        <ee:set-payload><![CDATA[%dw 2.0
output application/json
---
{message: "Not acceptable"}]]></ee:set-payload>
                    </ee:message>
                    <ee:variables>
                        <ee:set-variable variableName="httpStatus">406</ee:set-variable>
                    </ee:variables>
                </ee:transform>
            </on-error-propagate>
            <on-error-propagate type="APIKIT:UNSUPPORTED_MEDIA_TYPE" enableNotifications="true" logException="true">
                <ee:transform xsi:schemaLocation="http://www.mulesoft.org/schema/mule/ee/core http://www.mulesoft.org/schema/mule/ee/core/current/mule-ee.xsd">
                    <ee:message>
                        <ee:set-payload><![CDATA[%dw 2.0
output application/json
---
{message: "Unsupported media type"}]]></ee:set-payload>
                    </ee:message>
                    <ee:variables>
                        <ee:set-variable variableName="httpStatus">415</ee:set-variable>
                    </ee:variables>
                </ee:transform>
            </on-error-propagate>
            <on-error-propagate type="APIKIT:NOT_IMPLEMENTED" enableNotifications="true" logException="true">
                <ee:transform xsi:schemaLocation="http://www.mulesoft.org/schema/mule/ee/core http://www.mulesoft.org/schema/mule/ee/core/current/mule-ee.xsd">
                    <ee:message>
                        <ee:set-payload><![CDATA[%dw 2.0
output application/json
---
{message: "Not Implemented"}]]></ee:set-payload>
                    </ee:message>
                    <ee:variables>
                        <ee:set-variable variableName="httpStatus">501</ee:set-variable>
                    </ee:variables>
                </ee:transform>
            </on-error-propagate>
        </error-handler>
    </flow>
    <flow name="exampleprep-console">
        <http:listener config-ref="exampleprep-httpListenerConfig1" path="/console/*">
            <http:response statusCode="#[vars.httpStatus default 200]">
                <http:headers><![CDATA[#[vars.outboundHeaders default {}]]]></http:headers>
            </http:response>
            <http:error-response statusCode="#[vars.httpStatus default 500]">
                <http:body><![CDATA[#[payload]]]></http:body>
                <http:headers><![CDATA[#[vars.outboundHeaders default {}]]]></http:headers>
            </http:error-response>
        </http:listener>
        <apikit:console config-ref="exampleprep-config2" />
        <error-handler>
            <on-error-propagate type="APIKIT:NOT_FOUND" enableNotifications="true" logException="true">
                <ee:transform xsi:schemaLocation=" http://www.mulesoft.org/schema/mule/validation http://www.mulesoft.org/schema/mule/validation/current/mule-validation.xsd http://www.mulesoft.org/schema/mule/ee/core http://www.mulesoft.org/schema/mule/ee/core/current/mule-ee.xsd">
                    <ee:message>
                        <ee:set-payload><![CDATA[%dw 2.0
output application/json
---
{message: "Resource not found"}]]></ee:set-payload>
                    </ee:message>
                    <ee:variables>
                        <ee:set-variable variableName="httpStatus">404</ee:set-variable>
                    </ee:variables>
                </ee:transform>
            </on-error-propagate>
        </error-handler>
    </flow>
    <flow name="get:\main_uri\error\ContinueFlowRef:exampleprep-config2">
        <flow-ref doc:name="Flow Reference" doc:id="8d0bfcf0-9ba4-41e8-8dcd-6691d0bb022d" name="OnErrorContinueFlowRefMain" />
    </flow>
    <flow name="get:\main_uri\error\OnProgagateFlowRef:exampleprep-config2">
        <flow-ref doc:name="Flow Reference" doc:id="a5b65621-2129-4bb7-850a-6f3fa7afdbae" name="OnErrorPropagateFlowRefMain" />
    </flow>
    <flow name="get:\main_uri\subFlowVarPayloadTest:exampleprep-config2">
        <flow-ref doc:name="subFlowVarPayloadTest.xml" doc:id="6860a3ab-3cbe-4cfa-88f0-4c2935813eb1" name="get:main_uri\subFlowVarPayloadTest" />
    </flow>
    <flow name="get:\main_uri\scattergather\test1:exampleprep-config2">
        <flow-ref doc:name="Flow Reference" doc:id="173e734b-ec7c-4da1-a441-ff2db589a1e0" name="scatterGatherTest1"/>
    </flow>
	<flow name="get:\main_uri\error\ContinueSubFlowRef:exampleprep-config2">
        <flow-ref doc:name="Flow Reference" doc:id="617d7ff5-2f29-41e2-842a-93eac9244b56" name="OnErrorContinueSubFlowMain"/>
    </flow>
</mule>
